quantmax/__init__.py
quantmax/quantmax.py
quantmax-0.0.1.dist-info/METADATA
quantmax-0.0.1.dist-info/WHEEL
quantmax-0.0.1.dist-info/licenses/LICENSE
quantmax-0.0.1.dist-info/RECORD
