Metadata-Version: 2.4
Name: quantmax
Version: 0.0.1
Summary: Quantization made with Max efficiency.
License:                                  Apache License
License-File: LICENSE
Requires-Python: >=3.12
